pywce/__init__.py
pywce/modules/__init__.py
pywce/modules/logger/__init__.py
pywce/modules/session/__init__.py
pywce/modules/session/cachetool_session_manager.py
pywce/modules/session/dict_session_manager.py
pywce/modules/storage/__init__.py
pywce/modules/whatsapp/__init__.py
pywce/modules/whatsapp/config.py
pywce/modules/whatsapp/message_utils.py
pywce/modules/whatsapp/model/__init__.py
pywce/modules/whatsapp/model/message_type_enum.py
pywce/modules/whatsapp/model/response_structure.py
pywce/modules/whatsapp/model/wa_user.py
pywce/src/__init__.py
pywce/src/engine.py
pywce/src/constants/__init__.py
pywce/src/constants/engine.py
pywce/src/constants/session.py
pywce/src/constants/template.py
pywce/src/constants/template_type.py
pywce/src/exceptions/__init__.py
pywce/src/models/__init__.py
pywce/src/services/__init__.py
pywce/src/services/ai_service.py
pywce/src/services/hook_service.py
pywce/src/services/message_processor.py
pywce/src/services/template_message_processor.py
pywce/src/services/whatsapp_service.py
pywce/src/services/worker.py
pywce/src/templates/__init__.py
pywce/src/templates/base_model.py
pywce/src/templates/messages.py
pywce/src/templates/templates.py
pywce/src/utils/__init__.py
pywce/src/utils/engine_util.py
pywce/src/utils/hook_util.py
pywce-2.0.1.dist-info/licenses/LICENCE
pywce-2.0.1.dist-info/METADATA
pywce-2.0.1.dist-info/WHEEL
pywce-2.0.1.dist-info/top_level.txt
pywce-2.0.1.dist-info/RECORD
