Metadata-Version: 2.4
Name: pywce
Version: 2.0.1
Summary: A templates-driven framework for building WhatsApp chatbots
Home-page: https://github.com/DonnC/pywce
Author: Donald Chinhuru
Author-email: donychinhuru@gmail.com
License: MIT
Project-URL: Bug Tracker, https://github.com/DonnC/pywce/issues
Project-URL: Source Code, https://github.com/DonnC/pywce
Project-URL: Documentation, https://docs.page/donnc/wce
Keywords: whatsapp,chatbot,ai,yaml,automation,templates,hooks
Classifier: Development Status :: 4 - Beta
Classifier: Intended Audience :: Developers
Classifier: License :: OSI Approved :: MIT License
Classifier: Programming Language :: Python :: 3
Classifier: Programming Language :: Python :: 3.9
Classifier: Programming Language :: Python :: 3.10
Classifier: Programming Language :: Python :: 3.11
Classifier: Topic :: Software Development :: Libraries :: Python Modules
Classifier: Topic :: Communications :: Chat
Classifier: Operating System :: OS Independent
Requires-Python: >=3.9
License-File: LICENCE
Requires-Dist: python-dotenv
Requires-Dist: httpx~=0.28.1
Requires-Dist: ruamel.yaml~=0.18.10
Requires-Dist: requests-toolbelt~=1.0.0
Requires-Dist: Jinja2~=3.1.5
Provides-Extra: ai
Requires-Dist: openai; extra == "ai"
Requires-Dist: docstring-parser; extra == "ai"
Provides-Extra: cache
Requires-Dist: cachetools; extra == "cache"
Dynamic: author
Dynamic: author-email
Dynamic: classifier
Dynamic: description
Dynamic: description-content-type
Dynamic: home-page
Dynamic: keywords
Dynamic: license
Dynamic: license-file
Dynamic: project-url
Dynamic: provides-extra
Dynamic: requires-dist
Dynamic: requires-python
Dynamic: summary
